pmaw/Cache.py
pmaw/Metadata.py
pmaw/PushshiftAPI.py
pmaw/PushshiftAPIBase.py
pmaw/RateLimit.py
pmaw/Request.py
pmaw/Response.py
pmaw/__init__.py
pmaw/types/__init__.py
pmaw/types/exceptions.py
pmaw/utils/__init__.py
pmaw/utils/filter.py
pmaw/utils/slices.py
tests/__init__.py
tests/config.py
tests/test_cache.py
tests/test_filter_fn.py
tests/test_metadata.py
tests/test_request.py
tests/test_response.py
tests/test_search_comments.py
tests/test_search_submission_comment_ids.py
tests/test_search_submissions.py
tests/__mocks__/__init__.py
tests/__mocks__/comment.py
tests/__mocks__/metadata.py
tests/__mocks__/submission.py
pmaw-3.0.0.dist-info/LICENSE
pmaw-3.0.0.dist-info/METADATA
pmaw-3.0.0.dist-info/WHEEL
pmaw-3.0.0.dist-info/top_level.txt
pmaw-3.0.0.dist-info/RECORD
