Metadata-Version: 2.1
Name: pmaw
Version: 3.0.0
Summary: A multithread Pushshift.io API Wrapper for reddit.com comment and submission searches.
Home-page: https://github.com/mattpodolak/pmaw
Author: Matthew Podolak
Author-email: mpodola2@gmail.com
License: MIT License
Keywords: reddit api wrapper pushshift multithread data collection cache
Classifier: Development Status :: 3 - Alpha
Classifier: Programming Language :: Python :: 3 :: Only
Classifier: Programming Language :: Python :: 3.5
Classifier: Programming Language :: Python :: 3.6
Classifier: Programming Language :: Python :: 3.7
Classifier: Programming Language :: Python :: 3.8
Classifier: Programming Language :: Python :: 3.9
Classifier: Intended Audience :: Developers
Classifier: Topic :: Utilities
Classifier: License :: OSI Approved :: MIT License
Classifier: Operating System :: OS Independent
Requires-Python: >=3.5
License-File: LICENSE
